{"cameraMode":{"drawMode":0,"name":"Shaded","section":"Shading Mode"},"sceneLighting":true,"audioPlay":false,"sceneViewState":{"showFog":true,"showMaterialUpdate":false,"showSkybox":true,"showFlares":true,"showImageEffects":true,"showParticleSystems":true},"in2DMode":false,"pivot":{"x":-0.00008881092071533203,"y":4.895598411560059,"z":-2.8298802375793459},"rotation":{"x":-0.1981496959924698,"y":-0.1312931776046753,"z":0.026793304830789567,"w":-0.9709691405296326},"size":14.424949645996094,"orthographic":false}